danielpops/__init__.py
danielpops-0.0.1.dist-info/METADATA
danielpops-0.0.1.dist-info/WHEEL
danielpops-0.0.1.dist-info/top_level.txt
danielpops-0.0.1.dist-info/RECORD
