Metadata-Version: 2.1
Name: danielpops
Version: 0.0.1
Summary: Security research package
Home-page: UNKNOWN
Author: Daniel Popescu
Author-email: danielpops@gmail.com
License: UNKNOWN
Platform: UNKNOWN
Classifier: Programming Language :: Python :: 3
Classifier: Programming Language :: Python :: 2
